first_poetry_project_deenaawny/__init__.py
first_poetry_project_deenaawny-0.1.0.dist-info/METADATA
first_poetry_project_deenaawny-0.1.0.dist-info/WHEEL
first_poetry_project_deenaawny-0.1.0.dist-info/RECORD
