Metadata-Version: 2.1
Name: first-poetry-project-deenaawny
Version: 0.1.0
Summary: 
Author: deena
Author-email: awny.deena@gmail.com
Requires-Python: >=3.10,<4.0
Classifier: Programming Language :: Python :: 3
Classifier: Programming Language :: Python :: 3.10
Classifier: Programming Language :: Python :: 3.11
Classifier: Programming Language :: Python :: 3.12
Requires-Dist: pendulum (>=3.0.0,<4.0.0)
